README.txt
setup.cfg
setup.py
doc/Makefile
doc/contents.rst
doc/make.bat
doc/source/ChangeLog.rst
doc/source/Tutorial_ModelGraph.pdf
doc/source/conf.py
doc/source/index.rst
doc/source/network.png
doc/source/quickstart.rst
doc/source/references.rst
doc/source/tutorial.rst
share/data/LiverDREAM.csv
share/data/LiverDREAM.sif
share/data/README.txt
share/data/ToyModelMKM.csv
share/data/ToyModelMKM.sif
share/data/ToyModelT2.csv
share/data/ToyModelT2.sif
share/data/ToyODE.csv
share/data/ToyODE.png
share/data/ToyODE.sif
src/cellnopt/__init__.py
src/cellnopt.wrapper.egg-info/PKG-INFO
src/cellnopt.wrapper.egg-info/SOURCES.txt
src/cellnopt.wrapper.egg-info/dependency_links.txt
src/cellnopt.wrapper.egg-info/namespace_packages.txt
src/cellnopt.wrapper.egg-info/requires.txt
src/cellnopt.wrapper.egg-info/top_level.txt
src/cellnopt/wrapper/__init__.py
src/wrapper/__init__.py
src/wrapper/cnor.py
src/wrapper/data.py
src/wrapper/help.py
src/wrapper/modelSimResultsT1.pdf
src/wrapper/test.csv
src/wrapper/test.sif
src/wrapper/tools.py
src/wrapper/wrapper_cnor.py
src/wrapper/wrapper_dt.py
src/wrapper/wrapper_fuzzy.py
src/wrapper/wrapper_ode.py
test/cleanup.sh
test/test_CNOR_functional.py
test/test_CNOR_unit.py
test/test_R_example.py
test/test_cnor.py
test/test_cnor_ode.py
test/test_midas.py
test/test_plot_model.py
test/test_readsif.py
test/test_tools.py
test/test_wrapper_cno.py